README.rst
setup.cfg
setup.py
gutter/__init__.py
gutter.egg-info/PKG-INFO
gutter.egg-info/SOURCES.txt
gutter.egg-info/dependency_links.txt
gutter.egg-info/namespace_packages.txt
gutter.egg-info/not-zip-safe
gutter.egg-info/requires.txt
gutter.egg-info/top_level.txt
gutter/client/__init__.py
gutter/client/decorators.py
gutter/client/default.py
gutter/client/encoding.py
gutter/client/models.py
gutter/client/registry.py
gutter/client/settings.py
gutter/client/signals.py
gutter/client/singleton.py
gutter/client/testutils.py
gutter/client/wsgi.py
gutter/client/arguments/__init__.py
gutter/client/arguments/base.py
gutter/client/arguments/variables.py
gutter/client/operators/__init__.py
gutter/client/operators/comparable.py
gutter/client/operators/identity.py
gutter/client/operators/misc.py
gutter/client/operators/string.py