Metadata-Version: 1.1
Name: gutter
Version: 0.5.0
Summary: Client to gutter feature switches backend
Home-page: http://github.com/disqus/gutter
Author: DISQUS
Author-email: opensource@disqus.com
License: Apache License 2.0
Platform: UNKNOWN
Classifier: Development Status :: 2 - Pre-Alpha
Classifier: Intended Audience :: Developers
Classifier: Intended Audience :: System Administrators
Classifier: Operating System :: OS Independent
Classifier: Topic :: Software Development
